devtools/__init__.py
devtools/adapters/__init__.py
devtools/adapters/database/__init__.py
devtools/adapters/database/aiomysql.py
devtools/adapters/database/asyncmy.py
devtools/adapters/database/asyncpg.py
devtools/adapters/database/config.py
devtools/attrs/__init__.py
devtools/attrs/camel.py
devtools/attrs/converters/__init__.py
devtools/attrs/converters/json.py
devtools/attrs/converters/utils.py
devtools/attrs/field.py
devtools/attrs/helpers.py
devtools/attrs/main.py
devtools/attrs/methods.py
devtools/attrs/resolver.py
devtools/attrs/schema.py
devtools/attrs/shortcuts.py
devtools/attrs/utils/__init__.py
devtools/attrs/utils/factory.py
devtools/attrs/utils/functions.py
devtools/attrs/utils/typedef.py
devtools/cache/__init__.py
devtools/config/__init__.py
devtools/config/adapter/__init__.py
devtools/config/adapter/attrs.py
devtools/config/adapter/dataclass.py
devtools/config/adapter/dattrs.py
devtools/config/adapter/factory.py
devtools/config/adapter/helpers.py
devtools/config/adapter/interface.py
devtools/config/adapter/mark.py
devtools/config/adapter/pydantic.py
devtools/context/__init__.py
devtools/context/atomic_/__init__.py
devtools/context/atomic_/bound.py
devtools/context/atomic_/core.py
devtools/context/atomic_/resolver.py
devtools/context/context.py
devtools/context/interfaces/__init__.py
devtools/context/interfaces/adapter.py
devtools/context/typedef.py
devtools/database/__init__.py
devtools/database/adapter.py
devtools/database/config.py
devtools/database/context/__init__.py
devtools/database/context/asyncio.py
devtools/database/context/sync.py
devtools/database/drivers/__init__.py
devtools/database/drivers/dialect.py
devtools/database/drivers/interface.py
devtools/database/drivers/utils.py
devtools/database/entity.py
devtools/database/entity.pyi
devtools/database/metadata.py
devtools/database/typedef.py
devtools/database/utils.py
devtools/env_vars/__init__.py
devtools/env_vars/config/__init__.py
devtools/env_vars/config/_helpers.py
eric_devtools-0.3.3.dist-info/METADATA
eric_devtools-0.3.3.dist-info/WHEEL
eric_devtools-0.3.3.dist-info/RECORD
